django_mpesa/__init__.py
django_mpesa/admin.py
django_mpesa/apps.py
django_mpesa/conf.py
django_mpesa/models.py
django_mpesa/serializers.py
django_mpesa/tests.py
django_mpesa/urls.py
django_mpesa/views.py
django_mpesa/migrations/__init__.py
django_mpesa_tek-0.1.dist-info/LICENSE
django_mpesa_tek-0.1.dist-info/METADATA
django_mpesa_tek-0.1.dist-info/WHEEL
django_mpesa_tek-0.1.dist-info/top_level.txt
django_mpesa_tek-0.1.dist-info/RECORD
