Metadata-Version: 2.1
Name: django-mpesa-tek
Version: 0.1
Summary: A Django app to Include Mpesa Payments in your app.
Home-page: https://github.com/TralahM/django-mpesa
Author: Tralah M Brian
Author-email: briantralah@gmail.com
License: MIT
Platform: UNKNOWN
Classifier: Environment :: Web Environment
Classifier: Framework :: Django
Classifier: Intended Audience :: Developers
Classifier: License :: OSI Approved :: MIT License
Classifier: Operating System :: OS Independent
Classifier: Programming Language :: Python
Classifier: Programming Language :: Python :: 3
Classifier: Programming Language :: Python :: 3 :: Only
Classifier: Programming Language :: Python :: 3.6
Classifier: Programming Language :: Python :: 3.7
Classifier: Programming Language :: Python :: 3.8
Classifier: Topic :: Internet :: WWW/HTTP
Classifier: Topic :: Internet :: WWW/HTTP :: Dynamic Content
Requires-Dist: django-rest-framework
Requires-Dist: daraja-mpesa ; python_version == "3"
Provides-Extra: docs
Requires-Dist: sphinx ; extra == 'docs'
Requires-Dist: sphinx-automodapi ; extra == 'docs'
